better_logger/__init__.py
better_loggers-1.0.1.dist-info/METADATA
better_loggers-1.0.1.dist-info/WHEEL
better_loggers-1.0.1.dist-info/RECORD
