Metadata-Version: 2.3
Name: better-loggers
Version: 1.0.1
Summary: BetterLogger is a simple and powerful logging package that makes it easy to display logs.
Author-email: yama-yeah <b1021091@fun.ac.jp>
Requires-Python: >=3.8
Requires-Dist: wcwidth>=0.2.13
